pibooth/__init__.py
pibooth/booth.py
pibooth/counters.py
pibooth/language.py
pibooth/printer.py
pibooth/states.py
pibooth/utils.py
pibooth/camera/__init__.py
pibooth/camera/base.py
pibooth/camera/gphoto.py
pibooth/camera/hybrid.py
pibooth/camera/opencv.py
pibooth/camera/rpi.py
pibooth/config/__init__.py
pibooth/config/menu.py
pibooth/config/parser.py
pibooth/fonts/Amatic-Bold.ttf
pibooth/fonts/AmaticSC-Regular.ttf
pibooth/fonts/DancingScript-Bold.ttf
pibooth/fonts/DancingScript-Regular.ttf
pibooth/fonts/Monoid-Bold.ttf
pibooth/fonts/Monoid-Regular.ttf
pibooth/fonts/Monoid-Retina.ttf
pibooth/fonts/Roboto-BoldItalic.ttf
pibooth/fonts/Roboto-LightItalic.ttf
pibooth/fonts/__init__.py
pibooth/pictures/__init__.py
pibooth/pictures/factory.py
pibooth/pictures/pool.py
pibooth/pictures/sizing.py
pibooth/pictures/assets/arrow.png
pibooth/pictures/assets/camera.png
pibooth/pictures/assets/capture_left.png
pibooth/pictures/assets/capture_right.png
pibooth/pictures/assets/finished_left.png
pibooth/pictures/assets/finished_right.png
pibooth/pictures/assets/hand.png
pibooth/pictures/assets/layout1.png
pibooth/pictures/assets/layout2.png
pibooth/pictures/assets/layout3.png
pibooth/pictures/assets/layout4.png
pibooth/pictures/assets/printer.png
pibooth/pictures/assets/printer_failure.png
pibooth/pictures/assets/printer_touch.png
pibooth/pictures/assets/processing.png
pibooth/plugins/__init__.py
pibooth/plugins/camera_plugin.py
pibooth/plugins/hookspecs.py
pibooth/plugins/lights_plugin.py
pibooth/plugins/picture_plugin.py
pibooth/plugins/printer_plugin.py
pibooth/plugins/view_plugin.py
pibooth/scripts/__init__.py
pibooth/scripts/count.py
pibooth/scripts/diagnostic.py
pibooth/scripts/fonts.py
pibooth/scripts/printer.py
pibooth/scripts/regenerate.py
pibooth/view/__init__.py
pibooth/view/background.py
pibooth/view/window.py
pibooth-2.0.8.dist-info/LICENSE
pibooth-2.0.8.dist-info/METADATA
pibooth-2.0.8.dist-info/WHEEL
pibooth-2.0.8.dist-info/entry_points.txt
pibooth-2.0.8.dist-info/top_level.txt
pibooth-2.0.8.dist-info/RECORD
