Metadata-Version: 2.1
Name: pibooth
Version: 2.0.8
Summary: A photo booth application in pure Python for the Raspberry Pi.
Home-page: https://github.com/pibooth/pibooth
Download-URL: https://github.com/pibooth/pibooth/archive/2.0.8.tar.gz
Author: Vincent Verdeil, Antoine Rousseaux
License: MIT license
Keywords: Raspberry Pi,camera,photobooth
Platform: unix
Platform: linux
Classifier: Development Status :: 5 - Production/Stable
Classifier: Environment :: Other Environment
Classifier: Intended Audience :: Developers
Classifier: Intended Audience :: End Users/Desktop
Classifier: License :: OSI Approved :: MIT License
Classifier: Operating System :: POSIX :: Linux
Classifier: Programming Language :: Python :: 3.6
Classifier: Programming Language :: Python :: 3.7
Classifier: Programming Language :: Python :: 3.8
Classifier: Programming Language :: Python :: 3.9
Classifier: Natural Language :: Danish
Classifier: Natural Language :: Dutch
Classifier: Natural Language :: English
Classifier: Natural Language :: French
Classifier: Natural Language :: German
Classifier: Natural Language :: Hungarian
Classifier: Natural Language :: Italian
Classifier: Natural Language :: Norwegian
Classifier: Natural Language :: Portuguese
Classifier: Natural Language :: Portuguese (Brazilian)
Classifier: Natural Language :: Spanish
Classifier: Topic :: Multimedia :: Graphics :: Capture :: Digital Camera
Requires-Python: >=3.6
License-File: LICENSE
Requires-Dist: Pillow (==9.2.0)
Requires-Dist: pygame (>=1.9.6)
Requires-Dist: pygame-menu (==4.0.7)
Requires-Dist: pygame-vkeyboard (>=2.0.8)
Requires-Dist: psutil (>=5.5.1)
Requires-Dist: pluggy (>=0.13.1)
Requires-Dist: gpiozero (>=1.5.1)
Requires-Dist: picamera (>=1.13) ; platform_machine >= "armv0l" and platform_machine <= "armv9l"
Requires-Dist: RPi.GPIO (>=0.7.0) ; platform_machine >= "armv0l" and platform_machine <= "armv9l"
Provides-Extra: doc
Requires-Dist: sphinx ; extra == 'doc'
Requires-Dist: sphinx-rtd-theme ; extra == 'doc'
Requires-Dist: sphinx-copybutton ; extra == 'doc'
Provides-Extra: dslr
Requires-Dist: gphoto2 (>=2.0.0) ; extra == 'dslr'
Provides-Extra: printer
Requires-Dist: pycups (>=1.9.73) ; extra == 'printer'
Requires-Dist: pycups-notify (>=0.0.4) ; extra == 'printer'
